hcli_hleg/__init__.py
hcli_hleg/__main__.py
hcli_hleg/config.py
hcli_hleg/hutils.py
hcli_hleg/package.py
hcli_hleg/cli/__init__.py
hcli_hleg/cli/cli.py
hcli_hleg/cli/hearings.json
hcli_hleg/cli/logger.py
hcli_hleg/cli/refresher.py
hcli_hleg/cli/service.py
hcli_hleg/cli/template.json
hcli_hleg/data/hcli_hleg.1
hcli_hleg-0.2.0.dist-info/LICENSE.txt
hcli_hleg-0.2.0.dist-info/METADATA
hcli_hleg-0.2.0.dist-info/WHEEL
hcli_hleg-0.2.0.dist-info/entry_points.txt
hcli_hleg-0.2.0.dist-info/top_level.txt
hcli_hleg-0.2.0.dist-info/RECORD
