Metadata-Version: 2.1
Name: hcli_hleg
Version: 0.2.0
Summary: HCLI hleg is a pypi wrapper that contains an HCLI sample application (hleg); hleg is a legislature bill aggregation service that helps facilitate rapid action by providing a useful list of bill hearings on a timeline to facilitate testifying (e.g. online testimony).
Author-email: Jeff Michaud <cometaj2@proton.me>
License: MIT
Project-URL: Homepage, https://github.com/cometaj2/hcli_hleg
Keywords: cli,client,server,connector,hypermedia,rest,generic,development
Classifier: Development Status :: 2 - Pre-Alpha
Classifier: Intended Audience :: Developers
Classifier: Topic :: Software Development
Classifier: License :: OSI Approved :: MIT License
Classifier: Programming Language :: Python :: 3.8
Classifier: Programming Language :: Python :: 3.9
Classifier: Programming Language :: Python :: 3.10
Classifier: Programming Language :: Python :: 3.11
Classifier: Programming Language :: Python :: 3.12
License-File: LICENSE.txt
Requires-Dist: requests[socks]==2.28.1
Requires-Dist: configparser==5.3.0
Requires-Dist: certifi==2024.8.30
Requires-Dist: apscheduler==3.10.4
Requires-Dist: xmltodict==0.13.0
